ansible_lint-26.1.0.dist-info/licenses/COPYING
ansiblelint/__init__.py
ansiblelint/__main__.py
ansiblelint/_mockings.py
ansiblelint/_version.py
ansiblelint/app.py
ansiblelint/cli.py
ansiblelint/config.py
ansiblelint/constants.py
ansiblelint/errors.py
ansiblelint/file_utils.py
ansiblelint/generate_docs.py
ansiblelint/loaders.py
ansiblelint/logger.py
ansiblelint/output.py
ansiblelint/py.typed
ansiblelint/requirements.py
ansiblelint/runner.py
ansiblelint/skip_utils.py
ansiblelint/stats.py
ansiblelint/text.py
ansiblelint/transformer.py
ansiblelint/types.py
ansiblelint/utils.py
ansiblelint/version.py
ansiblelint/yaml_utils.py
ansiblelint/_internal/__init__.py
ansiblelint/_internal/internal_error.md
ansiblelint/_internal/load-failure.md
ansiblelint/_internal/parser-error.md
ansiblelint/_internal/rules.py
ansiblelint/_internal/warning.md
ansiblelint/data/.yamllint
ansiblelint/data/profiles.yml
ansiblelint/formatters/__init__.py
ansiblelint/rules/__init__.py
ansiblelint/rules/args.md
ansiblelint/rules/args.py
ansiblelint/rules/avoid_implicit.md
ansiblelint/rules/avoid_implicit.py
ansiblelint/rules/command_instead_of_module.md
ansiblelint/rules/command_instead_of_module.py
ansiblelint/rules/command_instead_of_shell.md
ansiblelint/rules/command_instead_of_shell.py
ansiblelint/rules/complexity.md
ansiblelint/rules/complexity.py
ansiblelint/rules/conftest.py
ansiblelint/rules/deprecated_bare_vars.md
ansiblelint/rules/deprecated_bare_vars.py
ansiblelint/rules/deprecated_local_action.md
ansiblelint/rules/deprecated_local_action.py
ansiblelint/rules/deprecated_module.md
ansiblelint/rules/deprecated_module.py
ansiblelint/rules/empty_string_compare.md
ansiblelint/rules/empty_string_compare.py
ansiblelint/rules/fqcn.md
ansiblelint/rules/fqcn.py
ansiblelint/rules/galaxy.md
ansiblelint/rules/galaxy.py
ansiblelint/rules/galaxy_version_incorrect.md
ansiblelint/rules/galaxy_version_incorrect.py
ansiblelint/rules/ignore_errors.md
ansiblelint/rules/ignore_errors.py
ansiblelint/rules/inline_env_var.md
ansiblelint/rules/inline_env_var.py
ansible_lint-26.1.0.dist-info/METADATA
ansible_lint-26.1.0.dist-info/WHEEL
ansible_lint-26.1.0.dist-info/entry_points.txt
ansible_lint-26.1.0.dist-info/top_level.txt
ansible_lint-26.1.0.dist-info/RECORD
