Metadata-Version: 2.4
Name: ansible-lint
Version: 26.1.0
Summary: Checks playbooks for practices and behavior that could potentially be improved
Author-email: Will Thames <will@thames.id.au>
Maintainer-email: Ansible by Red Hat <info@ansible.com>
License-Expression: GPL-3.0-or-later
Project-URL: changelog, https://github.com/ansible/ansible-lint/releases
Project-URL: documentation, https://docs.ansible.com/projects/lint/
Project-URL: homepage, https://github.com/ansible/ansible-lint
Project-URL: repository, https://github.com/ansible/ansible-lint
Keywords: ansible,lint
Classifier: Development Status :: 5 - Production/Stable
Classifier: Environment :: Console
Classifier: Intended Audience :: Developers
Classifier: Intended Audience :: Information Technology
Classifier: Intended Audience :: System Administrators
Classifier: Operating System :: MacOS
Classifier: Operating System :: POSIX
Classifier: Programming Language :: Python
Classifier: Programming Language :: Python :: 3
Classifier: Programming Language :: Python :: 3 :: Only
Classifier: Programming Language :: Python :: 3.10
Classifier: Programming Language :: Python :: 3.11
Classifier: Programming Language :: Python :: 3.12
Classifier: Programming Language :: Python :: 3.13
Classifier: Programming Language :: Python :: 3.14
Classifier: Topic :: Software Development :: Quality Assurance
Classifier: Topic :: Software Development :: Testing
Classifier: Topic :: System :: Systems Administration
Classifier: Topic :: Utilities
Requires-Python: >=3.10
License-File: COPYING
Requires-Dist: ansible-compat>=25.8.2
Requires-Dist: ansible-core>=2.16.14
Requires-Dist: black>=24.3.0
Requires-Dist: cffi>=1.15.1
Requires-Dist: cryptography>=38
Requires-Dist: distro>=1.9.0
Requires-Dist: filelock>=3.8.2
Requires-Dist: jsonschema>=4.10.0
Requires-Dist: packaging>=22.0
Requires-Dist: pathspec<1.0.0,>=0.10.3
Requires-Dist: pyyaml>=6.0.1; python_version < "3.14"
Requires-Dist: pyyaml>=6.0.1; python_version >= "3.14"
Requires-Dist: referencing>=0.36.2
Requires-Dist: ruamel-yaml>=0.18.11
Requires-Dist: ruamel-yaml-clib>=0.2.12; python_version < "3.14"
Requires-Dist: subprocess-tee>=0.4.1
Requires-Dist: wcmatch>=8.1.2; python_version < "3.12"
Requires-Dist: wcmatch>=8.5.0; python_version >= "3.12"
Requires-Dist: yamllint>=1.34.0
Dynamic: license-file
